LICENSE
MANIFEST.in
setup.py
versiontools_support.py
taiga_contrib_letschat/__init__.py
taiga_contrib_letschat/api.py
taiga_contrib_letschat/apps.py
taiga_contrib_letschat/models.py
taiga_contrib_letschat/permissions.py
taiga_contrib_letschat/serializers.py
taiga_contrib_letschat/signal_handlers.py
taiga_contrib_letschat/tasks.py
taiga_contrib_letschat.egg-info/PKG-INFO
taiga_contrib_letschat.egg-info/SOURCES.txt
taiga_contrib_letschat.egg-info/dependency_links.txt
taiga_contrib_letschat.egg-info/top_level.txt
taiga_contrib_letschat/migrations/0001_initial.py
taiga_contrib_letschat/migrations/0002_auto_20150921_0848.py
taiga_contrib_letschat/migrations/0003_auto_20170221_1547.py
taiga_contrib_letschat/migrations/__init__.py
taiga_contrib_letschat/templates/taiga_contrib_letschat/change.jinja
taiga_contrib_letschat/templates/taiga_contrib_letschat/create.jinja
taiga_contrib_letschat/templates/taiga_contrib_letschat/delete.jinja
taiga_contrib_letschat/templates/taiga_contrib_letschat/field-diff.jinja