Metadata-Version: 1.1
Name: taiga-contrib-letschat
Version: 3.1
Summary: The Taiga plugin for LetsChat integration
Home-page: https://github.com/taigaio/taiga-contrib-letschat
Author: Andrea Stagi
Author-email: stagi.andrea@gmail.com
License: AGPL
Keywords: taiga,letschat,integration
Platform: UNKNOWN
Classifier: Programming Language :: Python
Classifier: Development Status :: 4 - Beta
Classifier: Framework :: Django
Classifier: Intended Audience :: Developers
Classifier: License :: OSI Approved :: GNU Affero General Public License v3
Classifier: Operating System :: OS Independent
Classifier: Programming Language :: Python
Classifier: Topic :: Internet :: WWW/HTTP
